nettlesome/__init__.py
nettlesome/entities.py
nettlesome/factors.py
nettlesome/formatting.py
nettlesome/groups.py
nettlesome/predicates.py
nettlesome/quantities.py
nettlesome/statements.py
nettlesome/terms.py
tests/__init__.py
tests/conftest.py
tests/test_assertions.py
tests/test_comparisons.py
tests/test_context.py
tests/test_explanations.py
tests/test_facts.py
tests/test_groups.py
tests/test_predicates.py
tests/test_quantities.py
tests/test_schemas.py
tests/test_spec.py
tests/test_statements.py
tests/test_terms.py
nettlesome-0.7.1.dist-info/METADATA
nettlesome-0.7.1.dist-info/WHEEL
nettlesome-0.7.1.dist-info/top_level.txt
nettlesome-0.7.1.dist-info/RECORD
