Metadata-Version: 2.2
Name: nettlesome
Version: 0.7.1
Summary: simplified semantic reasoning
Home-page: https://github.com/mscarey/nettlesome
Author: Matt Carey
Author-email: matt@authorityspoke.com
Project-URL: Bug Tracker, https://github.com/mscarey/nettlesome/issues
Project-URL: Documentation, https://nettlesome.readthedocs.io/en/latest/
Classifier: Development Status :: 3 - Alpha
Classifier: License :: Free To Use But Restricted
Classifier: Programming Language :: Python :: 3.8
Classifier: Programming Language :: Python :: 3.9
Classifier: Programming Language :: Python :: 3.10
Classifier: Operating System :: OS Independent
Classifier: Natural Language :: English
Requires-Python: >=3.8
